[{"act_energy":2547838.8000000003,"act_stb_energy":{"0":349806470.40000004,"1":275576256.00000006},"all_bank_idle_cycles":{"0":164912,"1":299680},"average_bandwidth":0.23264,"average_interarrival":220.032462173315,"average_power":1175.5290105000001,"average_read_latency":22.85071574642127,"channel":0,"epoch_num":1,"hbm_dual_cmds":0,"interarrival_latency[-0]":0,"interarrival_latency[0-9]":595,"interarrival_latency[10-19]":61,"interarrival_latency[100-]":2670,"interarrival_latency[20-29]":84,"interarrival_latency[30-39]":67,"interarrival_latency[40-49]":5,"interarrival_latency[50-59]":4,"interarrival_latency[60-69]":4,"interarrival_latency[70-79]":13,"interarrival_latency[80-89]":71,"interarrival_latency[90-99]":61,"num_act_cmds":299,"num_cycles":800000,"num_ondemand_pres":41,"num_pre_cmds":298,"num_read_cmds":1467,"num_read_row_hits":1314,"num_reads_done":1467,"num_ref_cmds":205,"num_refb_cmds":0,"num_srefe_cmds":0,"num_srefx_cmds":0,"num_write_buf_hits":0,"num_write_cmds":2160,"num_write_row_hits":2014,"num_writes_done":2168,"pre_stb_energy":{"0":64117785.6,"1":116515584.0},"rank_active_cycles":{"0":635088,"1":500320},"read_energy":4689705.600000001,"read_latency[-0]":0,"read_latency[0-19]":1306,"read_latency[100-119]":7,"read_latency[120-139]":1,"read_latency[140-159]":4,"read_latency[160-179]":3,"read_latency[180-199]":4,"read_latency[20-39]":101,"read_latency[200-]":23,"read_latency[40-59]":12,"read_latency[60-79]":4,"read_latency[80-99]":2,"ref_energy":120264480.00000003,"refb_energy":-0.0,"sref_cycles":{"0":0,"1":0},"sref_energy":{"0":0.0,"1":0.0},"total_energy":940423208.4000001,"write_energy":6905088.0,"write_latency[-0]":0,"write_latency[0-19]":0,"write_latency[100-119]":1,"write_latency[120-139]":20,"write_latency[140-159]":98,"write_latency[160-179]":66,"write_latency[180-199]":67,"write_latency[20-39]":42,"write_latency[200-]":1477,"write_latency[40-59]":325,"write_latency[60-79]":53,"write_latency[80-99]":11}]
